py_seeds/__init__.py
py_seeds/utils.py
py_seeds-0.0.2.dist-info/LICENSE
py_seeds-0.0.2.dist-info/METADATA
py_seeds-0.0.2.dist-info/WHEEL
py_seeds-0.0.2.dist-info/top_level.txt
py_seeds-0.0.2.dist-info/RECORD
