Metadata-Version: 2.1
Name: py-seeds
Version: 0.0.2
Summary: Seed function for random, torch, torch.cuda
Home-page: https://github.com/ZiUNO/py-seeds
Author: ZiUNO
Author-email: ziuno@qq.com
License: MIT
Platform: UNKNOWN
Requires-Python: >=3.6
License-File: LICENSE
Requires-Dist: numpy
Requires-Dist: torch
